{
  "text": [
    {
      "text": "2020",
      "variant": "h1"
    },
    {
      "text": "",
      "variant": "medium"
    }
  ],
  "collection": [
    {
      "container": {
        "variant": "cards.interactive"
      },
      "text": [
        {
          "text": "Innovation",
          "color": "beta"
        },
        {
          "text": "Strong Drill Results at Castle East",
          "color": "omegaDarker",
          "variant": "h5"
        },
        {
          "text": "Dec. 18: The company is seeing very good drill numbers as they continue to explore the Castle East property."
        }
      ],
      "images": [
        {
          "src": "../../../../assets/site/media/video-interviews/placeholder.jpg",
          "alt": "alt text"
        }
      ],
      "buttons": [
        {
          "text": "Watch Interview",
          "type": "VIDEO",
          "link": "https://www.youtube.com/embed/1-2cSkQc6Rg?autoplay=1&modestbranding=1&showinfo=0&rel=0",
          "variant": "secondary"
        }
      ]
    },
    {
      "container": {
        "variant": "cards.interactive"
      },
      "text": [
        {
          "text": "Innovation",
          "color": "beta"
        },
        {
          "text": "The Castle Property with 7.5 million inferred oz silver",
          "color": "omegaDarker",
          "variant": "h5"
        },
        {
          "text": "Sep 2: The first company to put a 43-101 compliant in-situ resource in the whole Cobalt camp."
        }
      ],
      "images": [
        {
          "src": "../../../../assets/site/media/video-interviews/placeholder.jpg",
          "alt": "alt text"
        }
      ],
      "buttons": [
        {
          "text": "Watch Interview",
          "type": "VIDEO",
          "link": "https://www.youtube.com/embed/2j4SAmn7nvg?autoplay=1&modestbranding=1&showinfo=0&rel=0",
          "variant": "secondary"
        }
      ]
    },
    {
      "container": {
        "variant": "cards.interactive"
      },
      "text": [
        {
          "text": "Innovation",
          "color": "beta"
        },
        {
          "text": "One2One Virtual Forum",
          "color": "omegaDarker",
          "variant": "h5"
        },
        {
          "text": "Aug. 21: Canada Silver Cobalt presents at Proactive One2One Virtual Forum"
        }
      ],
      "images": [
        {
          "src": "../../../../assets/site/media/video-interviews/placeholder.jpg",
          "alt": "alt text"
        }
      ],
      "buttons": [
        {
          "text": "Watch Interview",
          "type": "VIDEO",
          "link": "https://www.youtube.com/embed/epLimjSvLhU?autoplay=1&modestbranding=1&showinfo=0&rel=0",
          "variant": "secondary"
        }
      ]
    }
  ]
}
